accumulate/__init__.py
accumulate/py.typed
accumulate-2.0.2.dist-info/METADATA
accumulate-2.0.2.dist-info/WHEEL
accumulate-2.0.2.dist-info/licenses/LICENSE
accumulate-2.0.2.dist-info/RECORD
