Metadata-Version: 2.3
Name: accumulate
Version: 2.0.2
Summary: Inheritance for iterable attributes.
Project-URL: Repository, https://github.com/JacobHayes/pymiscuous/tree/master/accumulate
Author-email: Jacob Hayes <jacob.r.hayes@gmail.com>
License-Expression: MIT
License-File: LICENSE
Requires-Python: <4,>=3.12
